ctypesgen/VERSION
ctypesgen/__init__.py
ctypesgen/ctypedescs.py
ctypesgen/descriptions.py
ctypesgen/expressions.py
ctypesgen/libraryloader.py
ctypesgen/main.py
ctypesgen/messages.py
ctypesgen/options.py
ctypesgen/version.py
ctypesgen/parser/__init__.py
ctypesgen/parser/cdeclarations.py
ctypesgen/parser/cgrammar.py
ctypesgen/parser/cparser.py
ctypesgen/parser/ctypesparser.py
ctypesgen/parser/datacollectingparser.py
ctypesgen/parser/lex.py
ctypesgen/parser/lextab.py
ctypesgen/parser/parsetab.py
ctypesgen/parser/pplexer.py
ctypesgen/parser/preprocessor.py
ctypesgen/parser/yacc.py
ctypesgen/printer_json/__init__.py
ctypesgen/printer_json/printer.py
ctypesgen/printer_python/__init__.py
ctypesgen/printer_python/defaultheader.py
ctypesgen/printer_python/preamble.py
ctypesgen/printer_python/printer.py
ctypesgen/processor/__init__.py
ctypesgen/processor/dependencies.py
ctypesgen/processor/operations.py
ctypesgen/processor/pipeline.py
ctypesgen-1.1.0.dist-info/LICENSE
ctypesgen-1.1.0.dist-info/METADATA
ctypesgen-1.1.0.dist-info/WHEEL
ctypesgen-1.1.0.dist-info/entry_points.txt
ctypesgen-1.1.0.dist-info/top_level.txt
ctypesgen-1.1.0.dist-info/RECORD
